Workbook

Sheet Overview
A1: PROJECT: CROSS-FUNCTIONAL REVENUE OPERATIONS TRANSFORMATION — AROMA
A3: Project ID | B3: AROMA-REVOPS-2020 | C3: Sponsor | D3: CEO (chairs results-review meetings)
A4: Project Lead (PM) | B4: Thuy Van — COO (me) | C4: Technology team | D4: Tuấn Vũ · Trà Giang
A5: Start date | B5: 43836 | C5: Core project close | D5: 44377
A6: Post-project optimization | B6: Jun 2021 – Aug 2022 (data optimization tail; BI report v1 = Aug 2022)
A7: Functions involved | B7: Marketing · Telesales · Sales · Training · Accounting | C7: Geographic scope | D7: Multi-branch (Hanoi & HCMC)
A8: Platform | B8: In-house no-code/low-code (issue-based: workflow, automation, JQL, sync) | C8: Project type | D8: RevOps operational transformation
A10: PROJECT OBJECTIVES
A11: 1. Standardize a single customer process across all branches.
A12: 2. Digitize the full Lead-to-Cash funnel so every lead & transaction leaves a data trail.
A13: 3. Make stage-by-stage conversion measurable to optimize the funnel.
A14: 4. Enable revenue attribution to content creator, ad operator, telesales rep, and closer.
A15: 5. Eliminate data waste via automated routing, recall, and recycling of un-closed leads.
A16: 6. Wire compensation directly to operational data, with fair per-stage allocation.
A17: 7. Provide near-real-time cross-functional BI reporting to leadership.
A19: PROGRESS DASHBOARD (auto from 'WBS & Tasks')
A20: Metric | B20: Value | C20: Metric | D20: Value
A21: Total tasks | B21: =COUNTA('WBS & Tasks'!H5:H37) -> 26 | C21: Avg % complete | D21: =IFERROR(AVERAGE('WBS & Tasks'!I5:I37),0) -> 1
A22: Completed | B22: =COUNTIF('WBS & Tasks'!H5:H37,"Completed") -> 26 | C22: In progress | D22: =COUNTIF('WBS & Tasks'!H5:H37,"In Progress") -> 0
A23: Not started | B23: =COUNTIF('WBS & Tasks'!H5:H37,"Not Started") -> 0 | C23: On hold | D23: =COUNTIF('WBS & Tasks'!H5:H37,"On Hold") -> 0

Sheet Team & Participants
A1: PROJECT TEAM & PARTICIPANTS
A3: Role | B3: Name | C3: Function | D3: Involvement | E3: Key responsibilities
A4: Sponsor / Executive | B4: CEO | C4: Executive Board | D4: Sponsor · chairs results-review meetings | E4: Approves direction; reviews outcomes in periodic results meetings; removes blockers
A5: Project Lead (COO) | B5: Thùy Vân (me) | C5: Operations / Executive | D5: Owner · architect · delivery lead | E5: Designs the full RevOps system (process, data model, attribution, compensation); leads cross-functional rollout & change management
A6: Technology (1) | B6: Tuấn Vũ | C6: Technology | D6: Core contributor | E6: System configuration: workflow, automation, cross-object sync, recall/recycle engine
A7: Technology (2) | B7: Trà Giang | C7: Technology | D7: Core contributor | E7: Project/workflow setup; lead-routing engine; receipt & revenue configuration
A8: Marketing Lead | B8: Huyền Mai | C8: Marketing | D8: Contributor | E8: Lead generation; UTM/attribution inputs; campaign source setup
A9: Telesales Lead | B9: Hiền Nguyễn | C9: Telesales | D9: Contributor | E9: First-touch qualification; appointment booking; telesales process adoption
A10: Sales Lead — HN (Cầu Giấy) | B10: Hoàng Tuyết | C10: Sales | D10: Contributor (pilot & HN rollout) | E10: HN branches incl. pilot; sales-process feedback; staff training on the new process
A11: Sales Lead — HCM | B11: Phan Thơm | C11: Sales | D11: Contributor (HCM rollout) | E11: HCM branches; sales-process adoption & staff training
A12: Accounting Lead | B12: Thu Thủy | C12: Accounting | D12: Contributor | E12: Receipts; revenue recognition; compensation calculation inputs
A13: Training Lead | B13: Thùy Vân (COO — kiêm nhiệm) | C13: Training | D13: Contributor (COO also leads Training) | E13: Trial teaching/assessment; renewal (re-sell) motion
A15: Note: names in [brackets] are role placeholders — replace with the actual person. 'Thuy Van (me)' = project owner/COO.

Sheet Current-State
A1: CURRENT-STATE ASSESSMENT
A3: ID | B3: Problem area | C3: Current state (issue) | D3: Business impact | E3: Root cause | F3: Severity | G3: Resolution direction
A4: CS-01 | B4: Process | C4: Each branch ran a different process; leadership lacked real-site visibility | D4: No control, no cross-branch comparison | E4: Lack of standardization & operational governance | F4: High | G4: Standardize one process, enforced through the system
A5: CS-02 | B5: People | C5: Branch managers wanted autonomy, resisted oversight, externalized blame | D5: Blocked change adoption | E5: Legacy operating culture, low data transparency | F5: High | G5: Re-scope roles; pilot first; manage change psychology
A6: CS-03 | B6: Sales funnel | C6: Appointment/contact rate only ~12-13% | D6: Major funnel leak at intake | E6: Telesales lacked process/pressure; low talk time (0.6-0.9h) | F6: High | G6: Standardize telesales process, lead scoring, data-driven bonus
A7: CS-04 | B7: Sales funnel | C7: No stage-by-stage conversion measurement (MKT→appt→action→payment) | D7: Couldn't locate where the funnel leaked | E7: Fragmented, disconnected data | F7: High | G7: Digitize full funnel; enforce complete fields per stage
A8: CS-05 | B8: Data | C8: 10-20% of leads unworked; qualified prospects lost | D8: Lost potential revenue | E8: No lead rotation / continuous nurturing | F8: High | G8: Round-robin routing + automated recall/recycle
A9: CS-06 | B9: Data | C9: Reps hoarded personal pipelines; no rotation | D9: Data 'died' in personal accounts | E9: No data-ownership standard | F9: Medium | G9: Define data as company asset; recall after 3 months un-closed
A10: CS-07 | B10: Compensation | C10: Couldn't trace lead source or who did which stage | D10: Unfair incentives, low motivation | E10: No attribution model or per-stage data | F10: High | G10: UTM attribution + multi-touch allocation; acquisition credit
A11: CS-08 | B11: Reporting | C11: Disconnected Excel reports, per-branch templates, slow consolidation | D11: Delayed executive decisions | E11: No standardized data foundation or BI | F11: Medium | G11: Standard reporting framework + cross-functional BI dashboards

Sheet WBS & Tasks
A1: WORK BREAKDOWN STRUCTURE & TASK TRACKER
A3: WBS | B3: Task | C3: Assignee | D3: Participants | E3: Start | F3: Finish | G3: Days | H3: Status | I3: % Complete | J3: Depends | K3: Notes
A4: 1 | B4: P1. Diagnosis & Initiation
A5: 1.1 | B5: Survey current-state operations per branch | C5: Thùy Vân (COO — me) | D5: Hiền Nguyễn, Hoàng Tuyết, Phan Thơm | E5: 43836 | F5: 43843 | G5: =F5-E5 -> 7 | H5: Completed | I5: 1 | K5: Interviews + funnel data collection
A6: 1.2 | B6: Analyze funnel leakage & bottlenecks | C6: Thùy Vân (COO — me) | E6: 43843 | F6: 43850 | G6: =F6-E6 -> 7 | H6: Completed | I6: 1 | J6: 1.1 | K6: Appointment/action stage = key focus
A7: 1.3 | B7: Confirm project objectives & scope | C7: Thùy Vân (COO — me) | D7: [CEO] | E7: 43845 | F7: 43852 | G7: =F7-E7 -> 7 | H7: Completed | I7: 1 | J7: 1.2 | K7: Charter reviewed with CEO
A8: 2 | B8: P2. Process & Data Design
A9: 2.1 | B9: Design Lead-to-Cash pipeline & state workflow | C9: Thùy Vân (COO — me) | D9: Tuấn Vũ, Trà Giang | E9: 43850 | F9: 43871 | G9: =F9-E9 -> 21 | H9: Completed | I9: 1 | J9: 1.3 | K9: 8 Deal states + Appointment workflow
A10: 2.2 | B10: Design multi-object data model | C10: Thùy Vân (COO — me) | D10: Trà Giang (Tech) | E10: 43857 | F10: 43878 | G10: =F10-E10 -> 21 | H10: Completed | I10: 1 | J10: 2.1 | K10: Deal↔Appt↔Contact↔Receipt↔Customer
A11: 2.3 | B11: Define field taxonomy | C11: Thùy Vân (COO — me) | D11: Huyền Mai, Thu Thủy | E11: 43864 | F11: 43881 | G11: =F11-E11 -> 17 | H11: Completed | I11: 1 | J11: 2.2 | K11: Attribution, source, status fields
A12: 2.4 | B12: Design lead-scoring framework (5-criteria ABCD) | C12: Thùy Vân (COO — me) | D12: Hiền Nguyễn, Hoàng Tuyết, Phan Thơm | E12: 43871 | F12: 43885 | G12: =F12-E12 -> 14 | H12: Completed | I12: 1 | J12: 2.3 | K12: Need/Product/Finance/Location/Timing
A13: 3 | B13: P3. System Configuration
A14: 3.1 | B14: Create project cluster (CRM, Appt, Receipt, Revenue, Class) | C14: Trà Giang (Tech) | D14: Tuấn Vũ (Tech) | E14: 43881 | F14: 43895 | G14: =F14-E14 -> 14 | H14: Completed | I14: 1 | J14: 2.2 | K14: Partitioned by region
A15: 3.2 | B15: Configure workflow, screens, fields, permissions | C15: Tuấn Vũ (Tech) | D15: Trà Giang (Tech) | E15: 43885 | F15: 43900 | G15: =F15-E15 -> 15 | H15: Completed | I15: 1 | J15: 3.1 | K15: Validators enforce fields per stage
A16: 3.3 | B16: Automation & cross-object sync | C16: Tuấn Vũ (Tech) | D16: Trà Giang (Tech) | E16: 43890 | F16: 43905 | G16: =F16-E16 -> 15 | H16: Completed | I16: 1 | J16: 3.2 | K16: Deal→Contact→Receipt auto-generation
A17: 3.4 | B17: Lead-routing engine (weighted round-robin) + accept status | C17: Trà Giang (Tech) | D17: Tuấn Vũ, Hiền Nguyễn | E17: 43891 | F17: 43910 | G17: =F17-E17 -> 19 | H17: Completed | I17: 1 | J17: 3.3 | K17: JQL filters by lead source
A18: 3.5 | B18: Data recall & recycling on schedule | C18: Tuấn Vũ (Tech) | D18: Thùy Vân (COO — me) | E18: 43900 | F18: 43921 | G18: =F18-E18 -> 21 | H18: Completed | I18: 1 | J18: 3.4 | K18: Recall >3 months; block rotation
A19: 4 | B19: P4. Attribution & Compensation
A20: 4.1 | B20: Standardize UTM & attribution fields (locked) | C20: Thùy Vân (COO — me) | D20: Huyền Mai, Tuấn Vũ | E20: 43891 | F20: 43905 | G20: =F20-E20 -> 14 | H20: Completed | I20: 1 | J20: 3.3 | K20: utm_* + content/ad custom fields
A21: 4.2 | B21: Design time-decay attribution model | C21: Thùy Vân (COO — me) | E21: 43900 | F21: 43915 | G21: =F21-E21 -> 15 | H21: Completed | I21: 1 | J21: 4.1 | K21: 0-3m 100% / 3-6m 60% / 6-12m 30%
A22: 4.3 | B22: Design per-stage revenue allocation | C22: Thùy Vân (COO — me) | D22: Hiền Nguyễn, Hoàng Tuyết, Phan Thơm | E22: 43905 | F22: 43921 | G22: =F22-E22 -> 16 | H22: Completed | I22: 1 | J22: 4.2 | K22: Tele 50% / Close 50%; acquisition separate
A23: 4.4 | B23: Build bonus formula + quality-adjustment coefficient | C23: Thùy Vân (COO — me) | D23: Thu Thủy (Accounting Lead) | E23: 43910 | F23: 43936 | G23: =F23-E23 -> 26 | H23: Completed | I23: 1 | J23: 4.3 | K23: 4 salary tiers; ABCD coeff; manager override
A24: 5 | B24: P5. Pilot
A25: 5.1 | B25: Trial the new process on a test project | C25: Tuấn Vũ (Tech) | D25: Thùy Vân, Huyền Mai | E25: 43918 | F25: 43931 | G25: =F25-E25 -> 13 | H25: Completed | I25: 1 | J25: 3.5 | K25: MKT data push + sales process test
A26: 5.2 | B26: Pilot rollout at one branch (Hoang Cau) | C26: Thùy Vân (COO — me) | D26: Hoàng Tuyết | E26: 43922 | F26: 43966 | G26: =F26-E26 -> 44 | H26: Completed | I26: 1 | J26: 5.1 | K26: Prove at one site first
A27: 5.3 | B27: Train staff & refine process | C27: Thùy Vân (COO — me) | D27: Hoàng Tuyết | E27: 43936 | F27: 43982 | G27: =F27-E27 -> 46 | H27: Completed | I27: 1 | J27: 5.2 | K27: Onboard new staff to standard process
A28: 6 | B28: P6. Cross-Branch Rollout
A29: 6.1 | B29: Roll out to Hanoi branches | C29: Thùy Vân (COO — me) | D29: Hoàng Tuyết | E29: 43983 | F29: 44135 | G29: =F29-E29 -> 152 | H29: Completed | I29: 1 | J29: 5.3 | K29: Cau Giay, Hoang Cau...
A30: 6.2 | B30: Roll out to HCMC branches | C30: Thùy Vân (COO — me) | D30: Phan Thơm | E30: 44075 | F30: 44286 | G30: =F30-E30 -> 211 | H30: Completed | I30: 1 | J30: 6.1 | K30: Region-split projects/accounts
A31: 6.3 | B31: Standardize periodic staffing/ops reporting | C31: Thùy Vân (COO — me) | D31: Hiền Nguyễn, Hoàng Tuyết, Phan Thơm | E31: 44013 | F31: 44347 | G31: =F31-E31 -> 334 | H31: Completed | I31: 1 | J31: 6.1 | K31: Continuous reporting to managers & reps
A32: 7 | B32: P7. Reporting Framework & Handover
A33: 7.1 | B33: Design standard reporting framework ('aroma way') | C33: Thùy Vân (COO — me) | D33: [CEO] | E33: 44197 | F33: 44316 | G33: =F33-E33 -> 119 | H33: Completed | I33: 1 | J33: 6.3 | K33: Situation→issues→assessment→solution
A34: 7.2 | B34: Documentation & handover; project close | C34: Thùy Vân (COO — me) | D34: Tuấn Vũ, Trà Giang | E34: 44317 | F34: 44377 | G34: =F34-E34 -> 60 | H34: Completed | I34: 1 | J34: 7.1 | K34: Core project completion (Q2 2021)
A35: 8 | B35: P8. Post-Project Data Optimization
A36: 8.1 | B36: Ongoing data optimization & cleanup | C36: Thùy Vân (COO — me) | D36: Tuấn Vũ, Trà Giang | E36: 44348 | F36: 44804 | G36: =F36-E36 -> 456 | H36: Completed | I36: 1 | J36: 7.2 | K36: Post-project; not part of core delivery
A37: 8.2 | B37: Build cross-functional BI report v1 | C37: Thùy Vân (COO — me) | D37: [CEO] | E37: 44562 | F37: 44804 | G37: =F37-E37 -> 242 | H37: Completed | I37: 1 | J37: 8.1 | K37: Reviewed with CEO in results meeting; v1 = Aug 2022

Sheet Milestones
A1: PROJECT MILESTONES
A3: ID | B3: Milestone | C3: Phase | D3: Owner | E3: Target date | F3: Actual date | G3: Status | H3: Notes
A4: M1 | B4: Diagnosis complete & scope confirmed | C4: P1 | D4: Thùy Vân (COO — me) | E4: 43852 | F4: 43852 | G4: Completed | H4: Charter reviewed with CEO
A5: M2 | B5: Process & data model design signed off | C5: P2 | D5: Thùy Vân (COO — me) | E5: 43885 | F5: 43887 | G5: Completed | H5: 2-day slip
A6: M3 | B6: System configured, ready for pilot | C6: P3 | D6: Tuấn Vũ (Tech) | E6: 43921 | F6: 43923 | G6: Completed
A7: M4 | B7: Attribution & compensation approved | C7: P4 | D7: Thùy Vân (COO — me) | E7: 43936 | F7: 43936 | G7: Completed
A8: M5 | B8: Successful pilot at one branch | C8: P5 | D8: Thùy Vân (COO — me) | E8: 43982 | F8: 43982 | G8: Completed | H8: Hoang Cau branch
A9: M6 | B9: Rollout complete across HN & HCMC | C9: P6 | D9: Thùy Vân (COO — me) | E9: 44286 | F9: 44301 | G9: Completed | H9: HCMC slipped slightly
A10: M7 | B10: Reporting framework, handover — PROJECT CLOSE | C10: P7 | D10: Thùy Vân (COO — me) | E10: 44377 | F10: 44377 | G10: Completed | H10: Core project close (Q2 2021)
A11: M8 | B11: BI report v1 (post-project optimization snapshot) | C11: P8 | D11: Thùy Vân (COO — me) | E11: 44804 | F11: 44804 | G11: Completed | H11: Reviewed with CEO; downstream evidence, not a project deliverable

Sheet KPIs
A1: KEY PERFORMANCE INDICATORS (BASELINE — TARGET — ACHIEVED)
A3: ID | B3: KPI | C3: Unit | D3: Baseline | E3: Target | F3: Stabilized | G3: Peak | H3: Delta (pp) | I3: Relative gain | J3: Source / Notes
A4: K1 | B4: Appointment rate / MKT leads | C4: % | D4: 0.13 | E4: 0.2 | F4: 0.2 | G4: 0.3 | H4: =F4-D4 -> 0.07 | I4: =IFERROR(F4/D4-1,0) -> 0.53846154 | J4: Baseline from 2019-2020 funnel; ~30% at peak
A5: K2 | B5: Close rate (closed / actioned) | C5: % | D5: 0.36 | E5: 0.5 | F5: 0.5 | G5: 0.67 | H5: =F5-D5 -> 0.14 | I5: =IFERROR(F5/D5-1,0) -> 0.38888889 | J5: Matches BI report 08/2022 (~50%, up to ~67% by segment/period)
A6: K3 | B6: Unworked-lead rate | C6: % | D6: 0.15 | E6: 0.05 | F6: 0.05 | G6: 0.03 | H6: =F6-D6 -> -0.1 | I6: =IFERROR(F6/D6-1,0) -> -0.66666667 | J6: Baseline 10-20%; cut via auto routing & recall
A7: K4 | B7: Telesales talk time | C7: hrs/day | D7: 0.75 | E7: 2 | F7: 1.8 | G7: 2.2 | H7: =F7-D7 -> 1.05 | I7: =IFERROR(F7/D7-1,0) -> 1.4 | J7: Baseline 0.6-0.9h; up via process & quota pressure
A8: K5 | B8: Report consolidation time | C8: days | D8: 7 | E8: 1 | F8: 1 | G8: 1 | H8: =F8-D8 -> -6 | I8: =IFERROR(F8/D8-1,0) -> -0.85714286 | J8: From several days → near real-time via cross-functional BI

Sheet Risks & Issues
A1: RISK & ISSUE REGISTER
A3: ID | B3: Risk / Issue | C3: Category | D3: Likelihood | E3: Impact | F3: Severity | G3: Mitigation | H3: Owner | I3: Status
A4: R1 | B4: Change resistance from branch managers | C4: People | D4: High | E4: High | F4: High | G4: Re-scope roles; pilot first; manage psychology; transparent reporting | H4: Thùy Vân (COO — me) | I4: Resolved
A5: R2 | B5: Incomplete data entry by staff | C5: Operations | D5: High | E5: High | F5: High | G5: Validators per stage; locked attribution fields; auto-fill | H5: Tuấn Vũ (Tech) | I5: Resolved
A6: R3 | B6: Unfair comp when a customer passes many hands | C6: Compensation | D6: Medium | E6: High | F6: High | G6: Durable Contact model + time-decay attribution | H6: Thùy Vân (COO — me) | I6: Resolved
A7: R4 | B7: Wasted historical lead data | C7: Data | D7: High | E7: Medium | F7: Medium | G7: Scheduled recall/recycle engine; re-warm before redistribution | H7: Thùy Vân (COO — me) | I7: Resolved
A8: R5 | B8: Technical risk in multi-object sync | C8: Technical | D8: Medium | E8: High | F8: High | G8: Test on staging project; monitor automation; manual fallback | H8: Trà Giang (Tech) | I8: Monitoring
A9: R6 | B9: Dependency on key personnel in operations | C9: Organization | D9: Medium | E9: Medium | F9: Medium | G9: Documented process; embed logic in system; succession training | H9: Thùy Vân (COO — me) | I9: Mitigated
A10: R7 | B10: External context affecting 2020 revenue | C10: External | D10: High | E10: High | F10: High | G10: Focus on conversion optimization & data recycling to offset intake | H10: Thùy Vân (COO — me) | I10: Mitigated
